LICENSE
MANIFEST.in
README.rst
setup.cfg
setup.py
cbvadmin_semantic_ui/__init__.py
cbvadmin_semantic_ui/settings.py
cbvadmin_semantic_ui.egg-info/PKG-INFO
cbvadmin_semantic_ui.egg-info/SOURCES.txt
cbvadmin_semantic_ui.egg-info/dependency_links.txt
cbvadmin_semantic_ui.egg-info/not-zip-safe
cbvadmin_semantic_ui.egg-info/requires.txt
cbvadmin_semantic_ui.egg-info/top_level.txt
cbvadmin_semantic_ui/static/cbvadmin/semantic-ui/cbvadmin.css
cbvadmin_semantic_ui/static/cbvadmin/semantic-ui/cbvadmin.js
cbvadmin_semantic_ui/static/cbvadmin/semantic-ui/jquery.min.js
cbvadmin_semantic_ui/static/vendor/moment/moment-with-locales.min.js
cbvadmin_semantic_ui/static/vendor/semantic-ui/semantic.css
cbvadmin_semantic_ui/static/vendor/semantic-ui/semantic.js
cbvadmin_semantic_ui/static/vendor/semantic-ui/semantic.min.css
cbvadmin_semantic_ui/static/vendor/semantic-ui/semantic.min.js
cbvadmin_semantic_ui/static/vendor/semantic-ui-calendar/calendar.min.css
cbvadmin_semantic_ui/static/vendor/semantic-ui-calendar/calendar.min.js
cbvadmin_semantic_ui/static/vendor/semantic-ui/themes/default/assets/fonts/icons.eot
cbvadmin_semantic_ui/static/vendor/semantic-ui/themes/default/assets/fonts/icons.otf
cbvadmin_semantic_ui/static/vendor/semantic-ui/themes/default/assets/fonts/icons.svg
cbvadmin_semantic_ui/static/vendor/semantic-ui/themes/default/assets/fonts/icons.ttf
cbvadmin_semantic_ui/static/vendor/semantic-ui/themes/default/assets/fonts/icons.woff
cbvadmin_semantic_ui/static/vendor/semantic-ui/themes/default/assets/fonts/icons.woff2
cbvadmin_semantic_ui/static/vendor/semantic-ui/themes/default/assets/images/flags.png
cbvadmin_semantic_ui/templates/cbvadmin/semantic-ui/base.html
cbvadmin_semantic_ui/templates/cbvadmin/semantic-ui/base_site.html
cbvadmin_semantic_ui/templates/cbvadmin/semantic-ui/change_form.html
cbvadmin_semantic_ui/templates/cbvadmin/semantic-ui/dashboard.html
cbvadmin_semantic_ui/templates/cbvadmin/semantic-ui/delete_confirm.html
cbvadmin_semantic_ui/templates/cbvadmin/semantic-ui/delete_modal.html
cbvadmin_semantic_ui/templates/cbvadmin/semantic-ui/edit_user.html
cbvadmin_semantic_ui/templates/cbvadmin/semantic-ui/filter.html
cbvadmin_semantic_ui/templates/cbvadmin/semantic-ui/list.html
