Metadata-Version: 1.2
Name: cbvadmin-semantic-ui
Version: 0.4.0
Summary: Semantic UI template for CBVadmin
Home-page: https://github.com/roldaojr/cbvadmin-semantic-ui
Author: roldaojr
Author-email: roldaogjr@gmail.com
License: MIT
Keywords: admin,django
Platform: UNKNOWN
Classifier: Environment :: Web Environment
Classifier: Framework :: Django
Classifier: Operating System :: OS Independent
Classifier: Programming Language :: JavaScript
Classifier: Programming Language :: Python :: 3.3
Classifier: Programming Language :: Python :: 3.4
Classifier: Programming Language :: Python :: 3.5
Classifier: Programming Language :: Python :: 3.6
Classifier: Topic :: Internet :: WWW/HTTP
Classifier: Topic :: Internet :: WWW/HTTP :: Dynamic Content
Classifier: Topic :: Software Development :: Libraries :: Python Modules
Requires-Python: >=3
